Workbook
Name dividir: Antecedentes!$D$2

Sheet Carátula
C7: ANÁLISIS COMPARATIVO DE MERCADO
C10: Insertar foto de fachada (tamaño 6 x 8 en horizontal o 6 x 4,5 en vertical)
BD26: VENTA
C27: DATOS DEL CLIENTE | BD27: ALQUILER
C29: Solicitante: | I29: PARDO | AF29: Fecha de Tasación: | AP29: 46162
C33: TELEFONO | M33: 3518 16-7298 | AF33: DESTINO: | AP33: VENTA | BD33: CASA
BD34: CASA EN PH
BD35: DEPTO EN PH
BD36: DUPLEX PH
C37: DATOS DEL INMUEBLE | BD37: LOCAL COMERCIAL
BD38: OFICINA
C39: DIRECCION | J39: ROSARIO DE STA FE | AF39: 2504 | BD39: CONSULTORIO
BD40: DEPOSITO
BD41: GALPON
BD42: INDUSTRIA
C43: PROPIEDAD: | L43: CASA | AF43: BARRIO: | AM43: YAPEYU | BD43: LOTE
BD44: CHACRA
BD45: CAMPO
BD46: EDIFICIO
C47: LOCALIDAD | L47: CORDOBA | AF47: PROVINCIA | AM47: CORDOBA | BD47: OTRO
C51: RESUMEN DE SUPERFICIES
C53: Superficie Terreno: | N53: 149 | Y53: m2 | AF53: Sup. construida: | AO53: 170 | AY53: m2
C57: Precio Dólar | N57: 1400 | Y57: U$S | AF57: Valor UVA´s | AO57: 1956.47
C82: MLS & MAINSTREET: Firmada la autorización de venta, su propiedad se integrará automáticamente al servicio de intranet CRM que utilizamos para promocionar de forma exclusiva las propiedades de nuestros clientes.
C86: 1 CARTEL: Colocaremos un cartel en su propiedad con nuestros numeros de teléfono celular para no perder un solo llamado.
C89: 2 SITIO WEB: bienenhaus.com.ar
C91: 3 OTROS SITIOS WEB: Será publicada la propiedad en los siguientes portales: www.zonaprop.com.ar; www.mercadolibre.com.ar; www.facebook.com; www.clasificadoslavoz.com.ar.
C95: 4 PROMOCIÓN A TRAVÉS DE FOLLETOS Y CARTAS: Serán enviados folletos y cartas a las inmobiliarias de la zona anunciando la venta de la propiedad.
C100: 5 COLABORACIÓN CON OTROS PROFESIONALES: Trabajamos en conjunto con otros colegas de manera de coordinar y cooperar en la venta de la propiedad. Sin embargo, Usted tratará sólo conmigo y canalizaré todas las gestiones de las otras inmobiliarias.
C104: 6 CARPETA DE PRESENTACIÓN: Para ayudar a que los posibles clientes recuerden su propiedad, una vez finalizada la visita, les entregaré una carpeta con las características de la misma, así como un plano de distribución y detalles de la zona donde se encuentra la propiedad destacando los mejores argumentos de venta. Así, el comprador, que lógicamente visita varias propiedades antes de decidirse, tendrá siempre la suya visible.
C109: 7 CUESTIONARIO: Utilizamos un cuestionario con cada potencial comprador, en donde hago una serie de preguntas que nos ayudan a conocer la reacción y comentarios sobre su propiedad.
C112: 8 SEGUIMIENTO: Mi experiencia me muestra que el seguimiento es tan clave como mostrar la propiedad. Le enviaré cada mes un amplio resumen de acciones de venta realizadas y el resultado obtenido, así como una lectura amplia de las opiniones de los interesados por su propiedad.
C115: 9 EVALUACIÓN: Cada 30 días nos juntaremos y haremos una evaluación de la actividad, el resultado y los comentarios obtenidos. En base a ellos ajustaremos nuestra estrategia.
C118: Con todo lo anteriormente expuesto, Usted puede estar tranquilo que la venta de su propiedad estará en buenas manos. Y si alguna vez durante el proceso de venta de su propiedad no estuviese de acuerdo con los pasos que sigo, o estima que no he cumplido con ellos, Usted puede notificármelo en cualquier momento y valoraremos lo ocurrido.
A133: DESCRIPCIÓN DE LA PROPIEDAD
A135: TIPO DE CONSTRUCCIÓN | O135: ESPACIO HABITABLE (m2) | Y135: CANTIDAD DE PLANTAS | AH135: AÑO DE CONSTRUCCIÓN / DE REMODELADO | AX135: VIDA REMANENTE
A136: Ladrillo | O136: 170 | Y136: PB+1 | AH136: 1955 | AQ136: 1981 | AX136: 70 | BE136: 2019
A138: PROM DE IMP. INMOBILIARIOS MENSUALES | S138: TIPO DE TECHO | AM138: ORIENTACIÓN | AW138: LUMINOSIDAD
A139: 9000 | S139: Losa H°A° | AM139: Sudoeste | AW139: Promedio
A141: CALIDAD CONSTRUCTIVA | Q141: CALIDAD DE MANTENIMIENTO | AD141: DETALLES DE TERMINACIÓN | AQ141: ESTACIONAMIENTO
A142: Media | Q142: Media | AD142: Medio | AQ142: Garaje cubierto
A144: AMBIENTES (INDICAR CANTIDAD) | AS144: COMODIDADES
A146: COCINA | J146: 1 | L146: DORMITORIOS | U146: 2 | W146: TERRAZA | AF146: 1 | AO146: DOBLE CIRCULACIÓN | AX146: N/A
A147: COMEDOR | L147: SUITE | W147: PATIO | AF147: 0 | AO147: ASADOR | AX147: Si
A148: COCINA-COMEDOR | L148: SUITE Y VESTIDOR | W148: BALCÓN | AO148: PISCINA | AX148: No
A149: LIVING | J149: 1 | L149: DORMIT. Y VESTIDOR | W149: LAVADERO | AO149: GARAGE / COCHERA | AX149: Si
A150: LIVING-COMEDOR | L150: BAÑO SERVICIO | W150: ESCRITORIO
A151: BAÑO | J151: 1 | L151: PLAY ROOM | W151: TOTAL CUARTOS
A152: CALEFACCIÓN | J152: Individual | Q152: AGUA CALIENTE | Z152: Individual | AG152: AIRE ACONDICIONADO | AP152: Individual
A154: CARACTERÍSTICAS ADVERSAS / DEFICIENCIAS:
A158: SERVICIOS
A159: ELECTRICIDAD | S159: GAS | AM159: TELÉFONO
A160: Público | S160: Público | AM160: Público
A161: AGUA | S161: CLOACA | AM161: DESAGUE PLUVIAL
A162: Público | S162: Público | AM162: Privado
B164: PLANO DE UBICACIÓN
B177: DESCRIPCIÓN DEL BARRIO
B179: TIPO | R179: CONSTRUIDO | AJ179: INDICE DE CRECIMIENTO | AU179: SERV. VIGILANCIA BARRIO
B180: Urbano | R180: Más del 75% | AJ180: Estable | AU180: No
B182: VALORES DE LA PROPIEDAD | T182: DEMANDA / OFERTA | AN182: TIEMPO DE COMERCIALIZACIÓN
B183: Decreciente | T183: Exceso de Oferta | AN183: Más de 6 meses
B185: USO DEL TERRENO % | T185: CAMBIOS PRINCIPALES EN EL USO DEL TERRENO | AN185: FACILIDADES DE ESTACIONAMIENTO TÍPICO
B186: 0.9 | E186: RESIDENCIAL | K186: 0.1 | N186: COMERCIAL | T186: Improbable | AN186: Garajes privados
E187: INDUSTRIAL | K187: =1-K186-B186-B187 -> 0 | N187: OTRO
B189: CARACTERÍSTICAS DEL BARRIO
B190: - | C190: Tipologías edilicias predominantes: | T190: Viviendas unifamiliares y PH de una planta
B191: - | C191: Calidad constructiva predominante: | T191: Media
B192: - | C192: Construcción en altura: | T192: No relevante o inexistente
B193: - | C193: Uso comercial: | T193: Sobre arterias principales
B194: - | C194: Uso industrial: | T194: No relevante o inexistente
B195: - | C195: Nivel socioeconómico: | T195: Medio Bajo

Sheet Resumen
A3: COMPARABLES
A5: COMPARABLE NRO 1 | G5: VALOR EN US$ | O5: VENTA O COTIZACIÓN | AB5: ANTIGÜEDAD | AC5: Estado | AD5: Estacionamiento | AE5: Ubicación | AF5: Comididaes | AG5: Habitaciones | AH5: CONSTRUIDOS
G6: =IF(A8="","",VLOOKUP(A8,Resumen1!B2:I7,5,FALSE)) -> 45000 | O6: Cotización | AA6: Superior | AB6: =+COUNTIF(A16,AA6) -> 0 | AC6: =+COUNTIF(J16,AA6) -> 0 | AD6: =+COUNTIF(Q16,AA6) -> 0 | AE6: =+COUNTIF(A19,AA6) -> 0 | AF6: =+COUNTIF(J19,AA6) -> 0 | AG6: =+COUNTIF(Q19,AA6) -> 0 | AI6: VU | AJ6: Valor | AK6: Año
A7: CALLE | I7: N° | K7: PISO/DEPTO | N7: BARRIO | S7: LOCALIDAD | X7: #VALUE! | AA7: Inferior | AB7: =+COUNTIF(A16,AA7) -> 1 | AC7: =+COUNTIF(J16,AA7) -> 0 | AD7: =+COUNTIF(Q16,AA7) -> 0 | AE7: =+COUNTIF(A19,AA7) -> 0 | AF7: =+COUNTIF(J19,AA7) -> 1 | AG7: =+COUNTIF(Q19,AA7) -> 0 | AH7: C1 | AI7: =IF(L10=0,"no",+G6/L10) -> 412.84404 | AJ7: =IF(L10=0,"no",G6) -> 45000 | AK7: =IF(L10=0,"no",G12) -> 1937
A8: PANAMA 2517 | N8: =IF(A8="","",VLOOKUP(A8,Resumen1!B2:I7,2,FALSE)) -> Yapeyú | S8: =Carátula!AM47 -> CORDOBA | AA8: Equivalente | AB8: =+COUNTIF(A16,AA8) -> 0 | AC8: =+COUNTIF(J16,AA8) -> 1 | AD8: =+COUNTIF(Q16,AA8) -> 1 | AE8: =+COUNTIF(A19,AA8) -> 1 | AF8: =+COUNTIF(J19,AA8) -> 0 | AG8: =+COUNTIF(Q19,AA8) -> 1 | AH8: C2 | AI8: =IF(L34=0,"no",+G30/L34) -> 310.45752 | AJ8: =IF(L34=0,"no",G30) -> 47500 | AK8: =IF(L34=0,"no",G36) -> 1954
A9: DIAS EN MERCADO | G9: TIPO DE PROPIEDAD | L9: ÁREA DE VIVIENDA | R9: SUPERFICIE DE TERRENO | AH9: C3 | AI9: =IF(L58=0,"no",+G54/L58) -> 437.5 | AJ9: =IF(L58=0,"no",G54) -> 35000 | AK9: =IF(L58=0,"no",G60) -> 1976
A10: =IF(A8="","",VLOOKUP(A8,Resumen1!B2:I7,6,FALSE)) -> 70 | G10: Casa unifamiliar | L10: =IF(A8="","",VLOOKUP(A8,Resumen1!B2:I7,4,FALSE)) -> 109 | R10: =IF(A8="","",VLOOKUP(A8,Resumen1!B2:I7,3,FALSE)) -> 200 | AH10: VT1 | AI10: =J26 -> 0 | AJ10: =X118 -> 62270.554 | AK10: no
A11: TIPO DE CONSTRUCCIÓN | G11: ANTIGÜEDAD | L11: PRECIO POR M2 | R11: FECHA DE REFERENCIA | AA11: Superior | AB11: =+IF(AB6=0,"0","1") -> 0 | AC11: =+IF(AC6=0,"0","1") -> 0 | AD11: =+IF(AD6=0,"0","1") -> 0 | AE11: =+IF(AE6=0,"0","1") -> 0 | AF11: =+IF(AF6=0,"0","1") -> 0 | AG11: =+IF(AG6=0,"0","1") -> 0 | AH11: VT2 | AI11: =IF(AH26="---","no",J26) -> 0 | AJ11: =IF(G6="---","no",G6) -> 45000 | AK11: no
A12: Ladrillo | G12: =IF(A8="","",VLOOKUP(A8,Resumen1!B2:I7,7,FALSE)) -> 1937 | L12: =+IF(L10=0,G6/R10,G6/L10) -> 412.84404 | R12: =Carátula!AP29 -> 46162 | AA12: Inferior | AB12: =+IF(AB7=0,"0","0,85") -> 0,85 | AC12: =+IF(AC7=0,"0","0,85") -> 0 | AD12: =+IF(AD7=0,"0","0,85") -> 0 | AE12: =+IF(AE7=0,"0","0,85") -> 0 | AF12: =+IF(AF7=0,"0","0,85") -> 0,85 | AG12: =+IF(AG7=0,"0","0,85") -> 0 | AH12: Mínimo | AI12: =+MIN(AI7:AI11) -> 0 | AJ12: =+MIN(AJ7:AJ11) -> 35000 | AK12: =+MIN(AK7:AK11) -> 1937
A14: COMPARACIÓN DE CARACTERÍSTICAS. | AA14: Equivalente | AB14: =+IF(AB8=0,"0","0,95") -> 0 | AC14: =+IF(AC8=0,"0","0,95") -> 0,95 | AD14: =+IF(AD8=0,"0","0,95") -> 0,95 | AE14: =+IF(AE8=0,"0","0,95") -> 0,95 | AF14: =+IF(AF8=0,"0","0,95") -> 0 | AG14: =+IF(AG8=0,"0","0,95") -> 0,95 | AH14: Máximo | AI14: =+MAX(AI7:AI11) -> 437.5 | AJ14: =+MAX(AJ7:AJ11) -> 62270.554
A15: ANTIGÜEDAD | J15: ESTADO DE MANTENIMIENTO | Q15: ESTACIONAMIENTO
A16: Inferior | J16: Equivalente | Q16: Equivalente
A18: CALIDAD DE UBICACIÓN | J18: COMODIDADES | Q18: CANT.DE HABITACIONES | AB18: =(AB11+AC11+AD11+AE11+AF11+AG11+AB12+AC12+AD12+AE12+AF12+AG12+AB14+AC14+AD14+AE14+AF14+AG14) -> 5.5
A19: Equivalente | J19: Inferior | Q19: Equivalente | AH19: TERRENOS
A21: INMOBILIARIA QUE COMERCIALIZA | P21: TELÉFONO | AB21: =L12*AB18 -> 2270.6422 | AI21: VU | AJ21: Valor
AB22: =L12/AB18 -> 75.062552 | AH22: C1 | AI22: =IF(L10=0,L12,"no") -> no | AJ22: =IF(L10=0,G6,"no") -> no
A23: OBSERVACIONES SOBRE DIFERENCIAS O SIMILITUDES CON LA PROPIEDAD TASADA. DESCRIPCIÓN DEL COMPARABLE | AH23: C2 | AI23: =IF(L34=0,L36,"no") -> no | AJ23: =IF(L34=0,G30,"no") -> no
A24: =IF(A8="","",VLOOKUP(A8,Resumen1!B2:I7,8,FALSE)) -> https://www.zonaprop.com.ar/propiedades/clasificado/veclcain-casa-en-venta-barrio-yapeyu-oportunidad-58581525.html?n_src=Listado&n_pg=1&n_pos=1 | AH24: C3 | AI24: =IF(L58=0,L60,"no") -> no | AJ24: =IF(L58=0,G54,"no") -> no
A25: VALOR DE LA PROPIEDAD TASADA EN RELACIÓN CON EL COMPARABLE 1 | X25: VALOR EN US$ | Y25: TIPO DE CAMBIO | AH25: VT1 | AI25: =AF30 -> 0 | AJ25: =AQ30 -> 0
A26: ENTRE | C26: =+IF(L10=0,ROUND(0.9*AJ26,-3),ROUND(0.9*AJ12,-3)) -> 32000 | G26: Y | H26: =+IF(L10=0,ROUND(1.1*AJ29,-3),ROUND(1.1*AJ14,-3)) -> 68000 | X26: =G6*Y26 -> 63000000 | Y26: =Carátula!N57 -> 1400 | AH26: Mínimo | AI26: =+MIN(AI22:AI25) -> 0 | AJ26: =+MIN(AJ22:AJ25) -> 0
A29: COMPARABLE NRO 2 | G29: VALOR EN US$ PRECIO | O29: VENTA O COTIZACIÓN | AB29: ANTIGÜEDAD | AC29: Estado | AD29: Estacionamiento | AE29: Ubicación | AF29: Comididaes | AG29: Habitaciones | AH29: Máximo | AI29: =+MAX(AI22:AI25) -> 0 | AJ29: =+MAX(AJ22:AJ25) -> 0
G30: =IF(A32="","",VLOOKUP(A32,Resumen1!B2:I7,5,FALSE)) -> 47500 | O30: Cotización | AA30: Superior | AB30: =+COUNTIF(A40,AA30) -> 0 | AC30: =+COUNTIF(J40,AA30) -> 0 | AD30: =+COUNTIF(Q40,AA30) -> 0 | AE30: =+COUNTIF(A43,AA30) -> 0 | AF30: =+COUNTIF(J43,AA30) -> 0 | AG30: =+COUNTIF(Q43,AA30) -> 0
A31: CALLE | I31: N° | K31: PISO/DEPTO | N31: BARRIO | S31: LOCALIDAD | X31: #VALUE! | AA31: Inferior | AB31: =+COUNTIF(A40,AA31) -> 1 | AC31: =+COUNTIF(J40,AA31) -> 0 | AD31: =+COUNTIF(Q40,AA31) -> 0 | AE31: =+COUNTIF(A43,AA31) -> 0 | AF31: =+COUNTIF($J$43,AA31) -> 1 | AG31: =+COUNTIF(Q43,AF31) -> 0
A32: Bailén 0 | N32: =IF(A32="","",VLOOKUP(A32,Resumen1!B2:I7,2,FALSE)) -> Yapeyú | S32: =Carátula!L47 -> CORDOBA | AA32: Equivalente | AB32: =+COUNTIF(A40,AA32) -> 0 | AC32: =+COUNTIF(J40,AA32) -> 1 | AD32: =+COUNTIF(Q40,AA32) -> 1 | AE32: =+COUNTIF(A43,AA32) -> 1 | AF32: =+COUNTIF($J$43,AA32) -> 0 | AG32: =+COUNTIF(Q43,AA32) -> 1
A33: DIAS EN MERCADO | G33: TIPO DE PROPIEDAD | L33: ÁREA DE VIVIENDA | R33: SUPERFICIE DE TERRENO | AJ33: +100/6+
A34: =IF(A32="","",VLOOKUP(A32,Resumen1!B2:I7,6,FALSE)) -> 12 | G34: Casa unifamiliar | L34: =IF(A32="","",VLOOKUP(A32,Resumen1!B2:I7,4,FALSE)) -> 153 | R34: =IF(A32="","",VLOOKUP(A32,Resumen1!B2:I7,3,FALSE)) -> 153
A35: TIPO DE CONSTRUCCIÓN | G35: AÑO DE CONSTRUCCIÓN | L35: PRECIO POR M2 | R35: FECHA DE REFERENCIA | AA35: Superior | AB35: =+IF(AB30=0,"0","1") -> 0 | AC35: =+IF(AC30=0,"0","1") -> 0 | AD35: =+IF(AD30=0,"0","1") -> 0 | AE35: =+IF(AE30=0,"0","1") -> 0 | AF35: =+IF(AF30=0,"0","1") -> 0 | AG35: =+IF(AG30=0,"0","1") -> 0
A36: Ladrillo | G36: =IF(A32="","",VLOOKUP(A32,Resumen1!B2:I7,7,FALSE)) -> 1954 | L36: =+IF(L34=0,G30/R34,G30/L34) -> 310.45752 | R36: =Carátula!AP29 -> 46162 | AA36: Inferior | AB36: =+IF(AB31=0,"0","0,85") -> 0,85 | AC36: =+IF(AC31=0,"0","0,85") -> 0 | AD36: =+IF(AD31=0,"0","0,85") -> 0 | AE36: =+IF(AE31=0,"0","0,85") -> 0 | AF36: =+IF(AF31=0,"0","0,85") -> 0,85 | AG36: =+IF(AG31=0,"0","0,85") -> 0
A38: COMPARACIÓN DE CARACTERÍSTICAS. | AA38: Equivalente | AB38: =+IF(AB32=0,"0","0,95") -> 0 | AC38: =+IF(AC32=0,"0","0,95") -> 0,95 | AD38: =+IF(AD32=0,"0","0,95") -> 0,95 | AE38: =+IF(AE32=0,"0","0,95") -> 0,95 | AF38: =+IF(AF32=0,"0","0,95") -> 0 | AG38: =+IF(AG32=0,"0","0,95") -> 0,95
A39: ANTIGÜEDAD | J39: ESTADO DE MANTENIMIENTO | Q39: ESTACIONAMIENTO
A40: Inferior | J40: Equivalente | Q40: Equivalente | AK40: +23/3
A42: CALIDAD DE UBICACIÓN | J42: COMODIDADES | Q42: CANT.DE HABITACIONES | AB42: =SUM(AB35+AC35+AD35+AE35+AF35+AG35+AB36+AC36+AD36+AE36+AF36+AG36+AB38+AC38+AD38+AE38+AF38+AG38) -> 5.5
A43: Equivalente | J43: Inferior | Q43: Equivalente
A45: INMOBILIARIA QUE COMERCIALIZA | P45: TELÉFONO
A47: OBSERVACIONES SOBRE DIFERENCIAS O SIMILITUDES CON LA PROPIEDAD TASADA. DESCRIPCIÓN DEL COMPARABLE
A48: =IF(A32="","",VLOOKUP(A32,Resumen1!B2:I7,8,FALSE)) -> https://www.zonaprop.com.ar/propiedades/clasificado/veclcain-vende-casa-dpto-en-barrio-yapeyu-59077706.html?n_src=Listado&n_pg=1&n_pos=1
A49: VALOR DE LA PROPIEDAD TASADA EN RELACIÓN CON EL COMPARABLE 2 | X49: PRECIO $ | Y49: TIPO DE CAMBIO | AB49: ,2 | AC49: ,15 | AD49: ,15 | AE49: ,1 | AF49: ,15 | AG49: ,15
A50: ENTRE | C50: =+IF(L34=0,ROUND(0.9*AJ26,-3),ROUND(0.9*AJ12,-3)) -> 32000 | G50: Y | H50: =+IF(L34=0,ROUND(1.1*AJ29,-3),ROUND(1.1*AJ14,-3)) -> 68000 | X50: =G30*Y50 -> 66500000 | Y50: =Carátula!N57 -> 1400
A53: COMPARABLE NRO 3 | G53: VALOR EN US$ | O53: VENTA O COTIZACIÓN | AB53: ANTIGÜEDAD | AC53: Estado | AD53: Estacionamiento | AE53: Ubicación | AF53: Comididaes | AG53: Habitaciones
G54: =IF(A56="","",VLOOKUP(A56,Resumen1!B2:I7,5,FALSE)) -> 35000 | O54: Cotización | AA54: Superior | AB54: =+COUNTIF(A64,AA54) -> 0 | AC54: =+COUNTIF(J64,AA54) -> 0 | AD54: =+COUNTIF(Q64,AA54) -> 0 | AE54: =+COUNTIF(A67,AA54) -> 0 | AF54: =+COUNTIF(J67,AA54) -> 0 | AG54: =+COUNTIF(Q67,AA54) -> 0 | AH54: =SUM(AB54:AG54) -> 0
A55: CALLE | I55: N° | K55: PISO/DEPTO | N55: BARRIO | S55: LOCALIDAD | X55: #VALUE! | AA55: Inferior | AB55: =+COUNTIF(A64,AA55) -> 1 | AC55: =+COUNTIF(J64,AA55) -> 0 | AD55: =+COUNTIF(Q64,AA55) -> 1 | AE55: =+COUNTIF(A67,AA55) -> 0 | AF55: =+COUNTIF(J67,AA55) -> 1 | AG55: =+COUNTIF(Q67,AF55) -> 0 | AH55: =SUM(AB55:AG55) -> 3
A56: Acoyte 79 | N56: =IF(A56="","",VLOOKUP(A56,Resumen1!B2:I7,2,FALSE)) -> Yapeyú | S56: =Carátula!L47 -> CORDOBA | AA56: Equivalente | AB56: =+COUNTIF(A64,AA56) -> 0 | AC56: =+COUNTIF(J64,AA56) -> 1 | AD56: =+COUNTIF(Q64,AA56) -> 0 | AE56: =+COUNTIF(A67,AA56) -> 1 | AF56: =+COUNTIF(J67,AA56) -> 0 | AG56: =+COUNTIF(Q67,AA56) -> 1 | AH56: =SUM(AB56:AG56) -> 3
A57: DIAS EN MERCADO | G57: TIPO DE PROPIEDAD | L57: ÁREA DE VIVIENDA | R57: SUPERFICIE DE TERRENO
A58: =IF(A56="","",VLOOKUP(A56,Resumen1!B2:I7,6,FALSE)) -> 365 | G58: Casa unifamiliar | L58: =IF(A56="","",VLOOKUP(A56,Resumen1!B2:I7,4,FALSE)) -> 80 | R58: =IF(A56="","",VLOOKUP(A56,Resumen1!B2:I7,3,FALSE)) -> 81
A59: TIPO DE CONSTRUCCIÓN | G59: AÑO DE CONSTRUCCIÓN | L59: PRECIO POR M2 | R59: FECHA DE REFERENCIA | AA59: Superior | AB59: =+IF(AB54=0,"0","1") -> 0 | AC59: =+IF(AC54=0,"0","1") -> 0 | AD59: =+IF(AD54=0,"0","1") -> 0 | AE59: =+IF(AE54=0,"0","1") -> 0 | AF59: =+IF(AF54=0,"0","1") -> 0 | AG59: =+IF(AG54=0,"0","1") -> 0
A60: Ladrillo | G60: =IF(A56="","",VLOOKUP(A56,Resumen1!B2:I7,7,FALSE)) -> 1976 | L60: =+IF(L58=0,G54/R58,G54/L58) -> 437.5 | R60: =Carátula!AP29 -> 46162 | AA60: Inferior | AB60: =+IF(AB55=0,"0","0,85") -> 0,85 | AC60: =+IF(AC55=0,"0","0,85") -> 0 | AD60: =+IF(AD55=0,"0","0,85") -> 0,85 | AE60: =+IF(AE55=0,"0","0,85") -> 0 | AF60: =+IF(AF55=0,"0","0,85") -> 0,85 | AG60: =+IF(AG55=0,"0","0,85") -> 0
A62: COMPARACIÓN DE CARACTERÍSTICAS. | AA62: Equivalente | AB62: =+IF(AB56=0,"0","0,95") -> 0 | AC62: =+IF(AC56=0,"0","0,95") -> 0,95 | AD62: =+IF(AD56=0,"0","0,95") -> 0 | AE62: =+IF(AE56=0,"0","0,95") -> 0,95 | AF62: =+IF(AF56=0,"0","0,95") -> 0 | AG62: =+IF(AG56=0,"0","0,95") -> 0,95
A63: ANTIGÜEDAD | J63: ESTADO DE MANTENIMIENTO | Q63: ESTACIONAMIENTO
A64: Inferior | J64: Equivalente | Q64: Inferior
A66: CALIDAD DE UBICACIÓN | J66: COMODIDADES | Q66: CANT.DE HABITACIONES | AB66: =SUM(AB59+AC59+AD59+AE59+AF59+AG59+AB60+AC60+AD60+AE60+AF60+AG60+AB62+AC62+AD62+AE62+AF62+AG62) -> 5.4
A67: Equivalente | J67: Inferior | Q67: Equivalente
A69: INMOBILIARIA QUE COMERCIALIZA | P69: TELÉFONO
A71: OBSERVACIONES SOBRE DIFERENCIAS O SIMILITUDES CON LA PROPIEDAD TASADA. DESCRIPCIÓN DEL COMPARABLE
A72: =IF(A56="","",VLOOKUP(A56,Resumen1!B2:I7,8,FALSE)) -> https://www.zonaprop.com.ar/propiedades/clasificado/veclcain-venta-casa-en-barrio-yapeyu-55797082.html?n_src=Listado&n_pg=1&n_pos=1
A73: VALOR DE LA PROPIEDAD TASADA EN RELACIÓN CON EL COMPARABLE 3 | X73: PRECIO $ | Y73: TIPO DE CAMBIO
A74: ENTRE | C74: =+IF(L58=0,ROUND(0.9*AJ26,-3),ROUND(0.9*AJ12,-3)) -> 32000 | G74: Y | H74: =+IF(L58=0,ROUND(1.1*AJ29,-3),ROUND(1.1*AJ14,-3)) -> 68000 | X74: =G54*Y74 -> 49000000 | Y74: =Carátula!N57 -> 1400
A79: ANALISIS COMPARATIVO
H81: 10 | P81: 10 | X81: PRECIO POR M2
B82: COMPARATIVO 1 | H82: =X82-(X82*$P$81/100) -> 371.55963 | P82: =X82+(X82*$P$81/100) -> 454.12844 | X82: =L12 -> 412.84404
B85: COMPARATIVO 2 | H85: =X85-(X85*$P$81/100) -> 279.41176 | P85: =X85+(X85*$P$81/100) -> 341.50327 | X85: =L36 -> 310.45752
B88: COMPARATIVO 3 | H88: =X88-(X88*$P$81/100) -> 393.75 | P88: =X88+(X88*$P$81/100) -> 481.25 | X88: =L60 -> 437.5
B91: PROMEDIO | H91: =AVERAGE(X82:X89) -> 386.93385 | P91: =(AVERAGE(AB18, AB42, AB66)+4)/10 -> 0.94666667 | X91: =H91*P91 -> 366.29738
A113: VALUACION | B113: VALUACIÓN
A116: COMPONENTES | J116: TOTAL M2 | Q116: PRECIO m2 ($) | X116: TOTAL $
A117: TERRENO | J117: =IF(Carátula!N53="""","""",Carátula!N53) -> 149
A118: SUPERFICIE CUBIERTA | J118: =IF(Carátula!AO53="""","""",Carátula!AO53) -> 170 | Q118: =X91 -> 366.29738 | X118: =(J118*Q118) -> 62270.554
A119: TOTAL
B133: DATOS DEL INMUEBLE
B135: DIRECCION | F135: =Carátula!J39 -> ROSARIO DE STA FE | R135: PISO
B138: BARRIO: | F138: =Carátula!AM43 -> YAPEYU | R138: LOCALIDAD | V138: =Carátula!L47 -> CORDOBA
B141: RESUMEN DE SUPERFICIES
B143: =Carátula!C53 -> Superficie Terreno: | I143: =Carátula!N53 -> 149 | P143: =Carátula!Y53 -> m2 | R143: =Carátula!AF53 -> Sup. construida: | X143: =Carátula!AO53 -> 170 | Y143: =Carátula!AY53 -> m2
B147: RESUMEN DE VALORES
B149: Valor de Mercado U$S | I149: =X118 -> 62270.554 | R149: Valor por m2 U$S: | X149: =Q118 -> 366.29738
B152: Valor de Mercado : | I152: =I149*Carátula!N57 -> 87178776 | R152: Valor por m2: | X152: =X149*Carátula!N57 -> 512816.33
B156: Valor Uva`s | I156: =I149*Carátula!AO57 -> 1.2183047e+08 | R156: Valor m2 Uva`s | X156: =X152/Carátula!AO57 -> 262.11306
E159: PRIMERA ENTREVISTA
E160: TOMA DE DATOS/INFORMACIÓN DE LA PROPIEDAD
E161: ENTREGA DE ANÁLISIS COMPARATIVO DE MERCADO
E162: ACUERDO DE COMERCIALIZACIÓN
E163: ENTREGA DOCUMENTACIÓN
E164: AUTORIZACIÓN FIRMADA POR TITULAR/ES DEL INMUEBLE
E165: FOTOCOPIA DNI TITULAR/ES DEL INMUEBLE
E166: FOTOCOPIA ESCRITURA / BOLETO
E167: FOTOCOPIA IMPUESTO DGR / MUNICIPAL
E168: FOTOCOPIA AGUA
E169: FOTOCOPIA ÚLTIMAS EXPENSAS
E170: FOTOCOPIA PLANOS DEL INMUEBLE
... E172: SOLICITUD INFORME DE DOMINIO

Sheet Resumen1
B1: Direccion | D1: Superficie | E1: Cubierta | F1: PRECIO | G1: Dias al mercado | H1: Antigüedad | I1: LINK
B2: =Antecedentes!B2 -> General Sandino 15 | C2: =Antecedentes!B3 -> Yapeyú | D2: =Antecedentes!B4 -> 180 | E2: =Antecedentes!B5 -> 107 | F2: =Antecedentes!B6 -> 65000 | G2: =Antecedentes!B7 -> 53 | H2: =Antecedentes!C8 -> 1986 | I2: =Antecedentes!B9 -> https://www.zonaprop.com.ar/propiedades/clasificado/veclcain-oportunidad-en-barrio-yapeyu-58720475.html?n_src=Listado&n_pg=1&n_pos=1
B3: =Antecedentes!B11 -> PANAMA 2517 | C3: =Antecedentes!B12 -> Yapeyú | D3: =Antecedentes!B13 -> 200 | E3: =Antecedentes!B14 -> 109 | F3: =Antecedentes!B15 -> 45000 | G3: =Antecedentes!B16 -> 70 | H3: =Antecedentes!C17 -> 1937 | I3: =Antecedentes!B18 -> https://www.zonaprop.com.ar/propiedades/clasificado/veclcain-casa-en-venta-barrio-yapeyu-oportunidad-58581525.html?n_src=Listado&n_pg=1&n_pos=1
B4: =Antecedentes!B20 -> Bailén 187 | C4: =Antecedentes!B21 -> Yapeyú | D4: =Antecedentes!B22 -> 150 | E4: =Antecedentes!B23 -> 81 | F4: =Antecedentes!B24 -> 43000 | G4: =Antecedentes!B25 -> 53 | H4: =Antecedentes!C26 -> 1956 | I4: =Antecedentes!B27 -> https://www.zonaprop.com.ar/propiedades/clasificado/veclcain-casa-de-2-dorm.-barrio-yapeyu-58725195.html?n_src=Listado&n_pg=1&n_pos=1
B5: =Antecedentes!B29 -> Bailén 0 | C5: =Antecedentes!B30 -> Yapeyú | D5: =Antecedentes!B31 -> 153 | E5: =Antecedentes!B32 -> 153 | F5: =Antecedentes!B33 -> 47500 | G5: =Antecedentes!B34 -> 12 | H5: =Antecedentes!C35 -> 1954 | I5: =Antecedentes!B36 -> https://www.zonaprop.com.ar/propiedades/clasificado/veclcain-vende-casa-dpto-en-barrio-yapeyu-59077706.html?n_src=Listado&n_pg=1&n_pos=1
B6: =Antecedentes!B38 -> Acoyte 79 | C6: =Antecedentes!B39 -> Yapeyú | D6: =Antecedentes!B40 -> 81 | E6: =Antecedentes!B41 -> 80 | F6: =Antecedentes!B42 -> 35000 | G6: =Antecedentes!B43 -> 365 | H6: =Antecedentes!C44 -> 1976 | I6: =Antecedentes!B45 -> https://www.zonaprop.com.ar/propiedades/clasificado/veclcain-venta-casa-en-barrio-yapeyu-55797082.html?n_src=Listado&n_pg=1&n_pos=1
B7: =Antecedentes!B47 -> Rosario de Santa Fe 2300 | C7: =Antecedentes!B48 -> Yapeyú | D7: =Antecedentes!B49 -> 170 | E7: =Antecedentes!B50 -> 79 | F7: =Antecedentes!B51 -> 45000 | G7: =Antecedentes!B52 -> 2 | H7: =Antecedentes!C53 -> 1966 | I7: =Antecedentes!B54 -> https://www.zonaprop.com.ar/propiedades/clasificado/veclcain-casa-en-barrio-yapeyu-59164338.html?n_src=Listado&n_pg=1&n_pos=1

Sheet Antecedentes
A1: 1 | H1: 1 | I1: =E2 -> 546.72897 | J1: =F2 -> 668.2243
A2: Direccion | B2: General Sandino 15 | D2: =+B6/B5 -> 607.47664 | E2: =+D2*0.9 -> 546.72897 | F2: =+D2*1.1 -> 668.2243 | G2: x | H2: 2 | I2: =E11 -> 371.55963 | J2: =F11 -> 454.12844 | N2: 2-3-6
A3: Barrio | B3: Yapeyú | H3: 3 | I3: =E20 -> 477.77778 | J3: =F20 -> 583.95062
A4: Superficie | B4: 180 | H4: 4 | I4: =E29 -> 279.41176 | J4: =F29 -> 341.50327
A5: Cubierta | B5: 107 | H5: 5 | I5: =E38 -> 393.75 | J5: =F38 -> 481.25
A6: Precio | B6: 65000 | H6: 6 | I6: =E47 -> 512.65823 | J6: =F47 -> 626.58228
A7: Dias al mercado | B7: 53
A8: Antigüedad | B8: 40 | C8: =2026-B8 -> 1986
A9: LINK | B9: https://www.zonaprop.com.ar/propiedades/clasificado/veclcain-oportunidad-en-barrio-yapeyu-58720475.html?n_src=Listado&n_pg=1&n_pos=1
A10: 2
A11: Direccion | B11: PANAMA 2517 | D11: =+B15/B14 -> 412.84404 | E11: =D11*0.9 -> 371.55963 | F11: =D11*1.1 -> 454.12844
A12: Barrio | B12: Yapeyú
A13: Superficie | B13: 200 | N13: +150000*40/100
A14: Cubierta | B14: 109
A15: Precio | B15: 45000
A16: Dias al mercado | B16: 70
A17: Antigüedad | B17: 89 | C17: =2026-B17 -> 1937
A18: LINK | B18: https://www.zonaprop.com.ar/propiedades/clasificado/veclcain-casa-en-venta-barrio-yapeyu-oportunidad-58581525.html?n_src=Listado&n_pg=1&n_pos=1
A19: 3
A20: Direccion | B20: Bailén 187 | D20: =B24/B23 -> 530.8642 | E20: =D20*0.9 -> 477.77778 | F20: =D20*1.1 -> 583.95062
A21: Barrio | B21: Yapeyú
A22: Superficie | B22: 150
A23: Cubierta | B23: 81
A24: Precio | B24: 43000
A25: Dias al mercado | B25: 53
A26: Antigüedad | B26: 70 | C26: =2026-B26 -> 1956
A27: LINK | B27: https://www.zonaprop.com.ar/propiedades/clasificado/veclcain-casa-de-2-dorm.-barrio-yapeyu-58725195.html?n_src=Listado&n_pg=1&n_pos=1
A28: 4
A29: Direccion | B29: Bailén 0 | D29: =B33/B32 -> 310.45752 | E29: =D29*0.9 -> 279.41176 | F29: =D29*1.1 -> 341.50327
A30: Barrio | B30: Yapeyú
A31: Superficie | B31: 153
A32: Cubierta | B32: 153
A33: Precio | B33: 47500
A34: Dias al mercado | B34: 12
A35: Antigüedad | B35: 72 | C35: =2026-B35 -> 1954
A36: LINK | B36: https://www.zonaprop.com.ar/propiedades/clasificado/veclcain-vende-casa-dpto-en-barrio-yapeyu-59077706.html?n_src=Listado&n_pg=1&n_pos=1
A37: 5
A38: Direccion | B38: Acoyte 79 | D38: =B42/B41 -> 437.5 | E38: =D38*0.9 -> 393.75 | F38: =D38*1.1 -> 481.25
A39: Barrio | B39: Yapeyú
A40: Superficie | B40: 81
A41: Cubierta | B41: 80
A42: Precio | B42: 35000
A43: Dias al mercado | B43: 365
A44: Antigüedad | B44: 50 | C44: =2026-B44 -> 1976
A45: LINK | B45: https://www.zonaprop.com.ar/propiedades/clasificado/veclcain-venta-casa-en-barrio-yapeyu-55797082.html?n_src=Listado&n_pg=1&n_pos=1
A46: 6
A47: Direccion | B47: Rosario de Santa Fe 2300 | D47: =B51/B50 -> 569.62025 | E47: =D47*0.9 -> 512.65823 | F47: =D47*1.1 -> 626.58228
A48: Barrio | B48: Yapeyú
A49: Superficie | B49: 170
A50: Cubierta | B50: 79
A51: Precio | B51: 45000
A52: Dias al mercado | B52: 2
A53: Antigüedad | B53: 60 | C53: =2026-B53 -> 1966
B54: https://www.zonaprop.com.ar/propiedades/clasificado/veclcain-casa-en-barrio-yapeyu-59164338.html?n_src=Listado&n_pg=1&n_pos=1

Sheet Hoja1
